dollarfmt/__init__.py
dollarfmt/core.py
dollarfmt/excel.py
dollarfmt/util.py
dollarfmt/tests/test_core.py
dollarfmt/tests/test_excel.py
dollarfmt-0.1.0.dist-info/METADATA
dollarfmt-0.1.0.dist-info/WHEEL
dollarfmt-0.1.0.dist-info/licenses/LICENSE
dollarfmt-0.1.0.dist-info/RECORD
