Metadata-Version: 2.4
Name: dollarfmt
Version: 0.1.0
Summary: A focused, dependency-light Python library for U.S. dollar currency formatting
Project-URL: Homepage, https://github.com/danjellesma/dollarfmt
Project-URL: Repository, https://github.com/danjellesma/dollarfmt
Project-URL: Issues, https://github.com/danjellesma/dollarfmt/issues
Author-email: Dan Jellesma <dollarfmt@aotclabs.com>
License: MIT
License-File: LICENSE
Keywords: currency,dollar,excel,finance,formatting
Classifier: Development Status :: 4 - Beta
Classifier: Intended Audience :: Developers
Classifier: Intended Audience :: Financial and Insurance Industry
Classifier: License :: OSI Approved :: MIT License
Classifier: Programming Language :: Python :: 3
Classifier: Programming Language :: Python :: 3.10
Classifier: Programming Language :: Python :: 3.11
Classifier: Programming Language :: Python :: 3.12
Classifier: Programming Language :: Python :: 3.13
Classifier: Topic :: Office/Business :: Financial
Classifier: Topic :: Software Development :: Libraries :: Python Modules
Classifier: Typing :: Typed
Requires-Python: >=3.10
Provides-Extra: dev
Requires-Dist: pytest-cov>=4.0.0; extra == 'dev'
Requires-Dist: pytest>=7.0.0; extra == 'dev'
Requires-Dist: ruff>=0.1.0; extra == 'dev'
